{
  "$id": "schema-object.json",
  "$schema": "http://json-schema.org/draft-07/schema#",
  "title": "Schema",
  "type": "object",
  "required": [
    "name",
    "slug"
  ],
  "properties": {
    "name": {
      "type": "string",
      "minLength": 3,
      "maxLength": 15
    },
    "slug": {
      "type": "string"
    },
    "createdOn": {
      "type": "string"
    },
    "lastUpdatedOn": {
      "type": "string"
    },
    "status": {
      "type": "string",
      "enum": [
        "Draft",
        "Review",
        "Live"
      ],
      "default": "Draft"
    },
    "visibility": {
      "type": "string",
      "enum": [
        "Default",
        "Parent"
      ],
      "default": "Default"
    },
    "artifactUrl": {
      "type": "string",
      "format": "url"
    },
    "description": {
      "type": "string"
    },
    "lastUpdatedBy": {
      "type": "string"
    },
    "lastPublishedBy": {
      "type": "string"
    },
    "lastPublishedOn": {
      "type": "string"
    }
  }
}